oneNuron/__init__.py
oneNuron/perceptron.py
oneNuron_pypi_rauthbibek-0.0.1.dist-info/LICENSE
oneNuron_pypi_rauthbibek-0.0.1.dist-info/METADATA
oneNuron_pypi_rauthbibek-0.0.1.dist-info/WHEEL
oneNuron_pypi_rauthbibek-0.0.1.dist-info/top_level.txt
oneNuron_pypi_rauthbibek-0.0.1.dist-info/RECORD
