Metadata-Version: 2.1
Name: oneNuron-pypi-rauthbibek
Version: 0.0.1
Summary: its an implimentation of Perceptron
Home-page: https://github.com/rauthbibek/oneNuron_pypi
Author: rauthbibek
Author-email: rauth.bibek66@gmail.com
License: UNKNOWN
Project-URL: Bug Tracker, https://github.com/rauthbibek/oneNuron_pypi/issues
Platform: UNKNOWN
Classifier: Programming Language :: Python :: 3
Classifier: License :: OSI Approved :: MIT License
Classifier: Operating System :: OS Independent
Requires-Python: >=3.7
License-File: LICENSE
Requires-Dist: numpy
Requires-Dist: tqdm
